{"displayTopicName":"Kavod","topicTokens":[{"text":"Kavod","type":"text"}],"paragraphsBySubtopic":{"Kavod":[{"tokens":[{"text":"Kavod is the concept in Judaism of a person wanting and receiving honor, praise, and having esteem in the eyes of others.","type":"text"}],"type":"text-line"},{"tokens":[{"text":"The desire for kavod is probably ","type":"text"}],"type":"text-line"},{"tokens":[{"text":"Is doing something for kavod wrong? When is it problematic and when not?","type":"text"}],"type":"text-line"}]}}